TwigORM/__init__.py
TwigORM/database/__init__.py
TwigORM/database/statement/__init__.py
TwigORM/database/statement/comparison.py
TwigORM-0.3.0.dist-info/LICENSE.txt
TwigORM-0.3.0.dist-info/METADATA
TwigORM-0.3.0.dist-info/WHEEL
TwigORM-0.3.0.dist-info/top_level.txt
TwigORM-0.3.0.dist-info/RECORD
