Metadata-Version: 2.1
Name: TwigORM
Version: 0.3.0
Summary: TwigORM is the ORM for the twig web framework.
Home-page: https://github.com/FrewtyPebbles/TwigORM
Author: William Lim
Author-email: William.Lim@csu.fullerton.edu
Project-URL: Bug Tracker, https://github.com/FrewtyPebbles/TwigORM/issues
Classifier: Programming Language :: Python :: 3
Classifier: License :: OSI Approved :: MIT License
Classifier: Operating System :: OS Independent
Requires-Python: >=3.7
License-File: LICENSE.txt
